merlin_ai_helper/__init__.py
merlin_ai_helper/core.py
merlin_ai_web_assistant-0.1.1.dist-info/METADATA
merlin_ai_web_assistant-0.1.1.dist-info/WHEEL
merlin_ai_web_assistant-0.1.1.dist-info/top_level.txt
merlin_ai_web_assistant-0.1.1.dist-info/RECORD
