Metadata-Version: 2.4
Name: merlin-ai-web-assistant
Version: 0.1.1
Summary: AI helper functions for a Flask web assistant using Groq.
Author-email: Merlin <your-email@example.com>
Requires-Python: >=3.8
Requires-Dist: groq>=0.9.0
